{
  "date": "2026-07-16",
  "effective_time": "12:00:00 AM",
  "unit": "CAD cents/litre before tax",
  "product": "E10",
  "prices": [
    {
      "product": "E10",
      "terminal": "Montreal",
      "price": 142.8
    },
    {
      "product": "E10",
      "terminal": "Quebec",
      "price": 142.8
    },
    {
      "product": "E10",
      "terminal": "Sept-Iles",
      "price": 152.5
    },
    {
      "product": "E10",
      "terminal": "Toronto",
      "price": 134.8
    },
    {
      "product": "E10",
      "terminal": "Hamilton",
      "price": 134.8
    },
    {
      "product": "E10",
      "terminal": "Nanticoke",
      "price": 134.3
    },
    {
      "product": "E10",
      "terminal": "London",
      "price": 133.8
    },
    {
      "product": "E10",
      "terminal": "Sarnia",
      "price": 133.3
    },
    {
      "product": "E10",
      "terminal": "Ottawa",
      "price": 136.3
    },
    {
      "product": "E10",
      "terminal": "Maitland",
      "price": 134.8
    },
    {
      "product": "E10",
      "terminal": "Belleville",
      "price": 136.9
    },
    {
      "product": "E10",
      "terminal": "Halifax",
      "price": 137.3
    },
    {
      "product": "E10",
      "terminal": "Sydney",
      "price": 139.8
    },
    {
      "product": "E10",
      "terminal": "Saint John",
      "price": 140.6
    },
    {
      "product": "E10",
      "terminal": "Chatham",
      "price": 130.4
    },
    {
      "product": "E10",
      "terminal": "Corner Brook",
      "price": 140.4
    }
  ],
  "collected_at": "2026-07-16T13:21:12+00:00",
  "source_url": "https://valeroapps.valero.com/public/rpt_Terminal_Rack_Prices.pdf",
  "source_sha256": "3d857e4026586546bd918e5a180db26fa5c4fa30f8462c1136a6797899206b4c"
}
